odoo/addons/base_changeset/README.rst
odoo/addons/base_changeset/__init__.py
odoo/addons/base_changeset/__manifest__.py
odoo/addons/base_changeset/demo/changeset_field_rule.xml
odoo/addons/base_changeset/i18n/base_changeset.pot
odoo/addons/base_changeset/i18n/ca.po
odoo/addons/base_changeset/i18n/es.po
odoo/addons/base_changeset/i18n/it.po
odoo/addons/base_changeset/i18n/tr.po
odoo/addons/base_changeset/i18n/tr_TR.po
odoo/addons/base_changeset/models/__init__.py
odoo/addons/base_changeset/models/base.py
odoo/addons/base_changeset/models/changeset_field_rule.py
odoo/addons/base_changeset/models/record_changeset.py
odoo/addons/base_changeset/models/record_changeset_change.py
odoo/addons/base_changeset/readme/CONFIGURE.rst
odoo/addons/base_changeset/readme/CONTRIBUTORS.rst
odoo/addons/base_changeset/readme/DESCRIPTION.rst
odoo/addons/base_changeset/readme/ROADMAP.rst
odoo/addons/base_changeset/readme/USAGE.rst
odoo/addons/base_changeset/security/groups.xml
odoo/addons/base_changeset/security/ir.model.access.csv
odoo/addons/base_changeset/security/rules.xml
odoo/addons/base_changeset/static/description/icon.png
odoo/addons/base_changeset/static/description/index.html
odoo/addons/base_changeset/static/src/components/changeset_popover.esm.js
odoo/addons/base_changeset/static/src/components/changeset_popover.scss
odoo/addons/base_changeset/static/src/components/changeset_popover.xml
odoo/addons/base_changeset/static/src/components/form_label.xml
odoo/addons/base_changeset/static/src/components/record.esm.js
odoo/addons/base_changeset/static/src/img/badge.png
odoo/addons/base_changeset/static/src/img/badge_click.png
odoo/addons/base_changeset/static/src/img/changeset.png
odoo/addons/base_changeset/static/src/img/rules.png
odoo/addons/base_changeset/tests/__init__.py
odoo/addons/base_changeset/tests/common.py
odoo/addons/base_changeset/tests/test_changeset_field_rule.py
odoo/addons/base_changeset/tests/test_changeset_field_type.py
odoo_addon_base_changeset-16.0.1.0.0.29.dist-info/METADATA
odoo_addon_base_changeset-16.0.1.0.0.29.dist-info/WHEEL
odoo_addon_base_changeset-16.0.1.0.0.29.dist-info/top_level.txt
odoo_addon_base_changeset-16.0.1.0.0.29.dist-info/RECORD
